langchain_chain_of_verification/__init__.py
langchain_chain_of_verification/cli.py
langchain_chain_of_verification/cove_chains.py
langchain_chain_of_verification/execute_verification_chain.py
langchain_chain_of_verification/prompts.py
langchain_chain_of_verification/route_chain.py
langchain_chain_of_verification/types.py
langchain_chain_of_verification-0.1.11.dist-info/METADATA
langchain_chain_of_verification-0.1.11.dist-info/WHEEL
langchain_chain_of_verification-0.1.11.dist-info/entry_points.txt
langchain_chain_of_verification-0.1.11.dist-info/RECORD
