Metadata-Version: 2.3
Name: langchain-chain-of-verification
Version: 0.1.11
Summary: Add your description here
License-Expression: MIT
Keywords: cli,langchain,prompt-engineering
Classifier: Topic :: Utilities
Requires-Python: >=3.10
Requires-Dist: duckduckgo-search>=6.2.13
Requires-Dist: langchain-community>=0.2.1
Requires-Dist: langchain==0.2.1
Requires-Dist: openai>=1.47.1
Requires-Dist: python-dotenv>=1.0.1
